pgn4people_poc/.DS_Store
pgn4people_poc/__init__.py
pgn4people_poc/__main__.py
pgn4people_poc/__version__.py
pgn4people_poc/build_tree.py
pgn4people_poc/classes_arboreal.py
pgn4people_poc/compile_and_output_report.py
pgn4people_poc/constants.py
pgn4people_poc/construct_output.py
pgn4people_poc/error_processing.py
pgn4people_poc/get_process_user_input.py
pgn4people_poc/jdr_utilities.py
pgn4people_poc/pgn4people.py
pgn4people_poc/pgn_utilities.py
pgn4people_poc/process_pgn_file.py
pgn4people_poc/strip_balanced_braces.py
pgn4people_poc/traverse_tree.py
pgn4people_poc/utilities.py
pgn4people_poc/__pycache__/__init__.cpython-39.pyc
pgn4people_poc/__pycache__/__main__.cpython-39.pyc
pgn4people_poc/__pycache__/__version__.cpython-39.pyc
pgn4people_poc/__pycache__/build_tree.cpython-39.pyc
pgn4people_poc/__pycache__/classes_arboreal.cpython-39.pyc
pgn4people_poc/__pycache__/compile_and_output_report.cpython-39.pyc
pgn4people_poc/__pycache__/constants.cpython-39.pyc
pgn4people_poc/__pycache__/construct_output.cpython-39.pyc
pgn4people_poc/__pycache__/error_processing.cpython-39.pyc
pgn4people_poc/__pycache__/errors.cpython-39.pyc
pgn4people_poc/__pycache__/get_process_user_input.cpython-39.pyc
pgn4people_poc/__pycache__/jdr_utilities.cpython-39.pyc
pgn4people_poc/__pycache__/pgn4people.cpython-39.pyc
pgn4people_poc/__pycache__/pgn_utilities.cpython-39.pyc
pgn4people_poc/__pycache__/process_CLI.cpython-39.pyc
pgn4people_poc/__pycache__/process_pgn_file.cpython-39.pyc
pgn4people_poc/__pycache__/strip_balanced_braces.cpython-39.pyc
pgn4people_poc/__pycache__/traverse_tree.cpython-39.pyc
pgn4people_poc/__pycache__/utilities.cpython-39.pyc
pgn4people_poc/example_pgns/.DS_Store
pgn4people_poc/example_pgns/__init__.py
pgn4people_poc/example_pgns/demo_pgn_1.pgn
pgn4people_poc/example_pgns/__pycache__/__init__.cpython-39.pyc
pgn4people_poc-1.0.0.dist-info/LICENSE
pgn4people_poc-1.0.0.dist-info/METADATA
pgn4people_poc-1.0.0.dist-info/WHEEL
pgn4people_poc-1.0.0.dist-info/entry_points.txt
pgn4people_poc-1.0.0.dist-info/top_level.txt
pgn4people_poc-1.0.0.dist-info/RECORD
