Metadata-Version: 2.1
Name: pgn4people-poc
Version: 1.0.0
Summary: Viewer of PGN for highly nested chess games and opening repertoires
Home-page: https://github.com/jimratliff/pgn4people-poc
Author: Jim Ratliff
Author-email: jim@jim-ratliff.name
Project-URL: Bug Tracker, https://github.com/jimratliff/pgn4people-poc/issues
Classifier: Programming Language :: Python :: 3.9
Classifier: License :: OSI Approved :: MIT License
Classifier: Operating System :: OS Independent
Classifier: Intended Audience :: Developers
Requires-Python: >=3.9
License-File: LICENSE
Requires-Dist: yachalk
